{
    "CAN_YOU_KEEP_A_SECRET": "Sır tutabilir misin<span class='simple-font'>?</span>",
    "IF_SO_DONT_CLICK_HERE": "Öyleyse buraya tıklamayın",

    "WE_DIDNT_THINK_YOU_COULD": "Yapabileceğini düşünmedik!",
    "NEITHER_CAN_WE_BUT_WE_NEED_TO_WAIT_UNTIL_MARCH_9TH_FOR": "Biz de yapamayız, ama yapmamız gerek<br>9 Mart'a kadar bekleyin, peki ne için?",
    "THE_BIG_REVEAL": "BÜYÜK İFŞA!",
    "THE_TIME_FOR_SOMETHING_NEW_IS_HERE": "Yeni bir şeyin zamanı geldi artık.",
    "THE_EVOLUTION_OF_THE_HOMEBASED_BUSINESS_INDUSTRY_BEGINS_NOW": "Ev merkezli ticaret endüstrisinin evrimi şimdi başlıyor.",
    "ON_MARCH_9_AT_1000_AM_CST_WE_START_THE_REVOLUTION": "9 Mart günü MST (Merkezi Standart Saat) ile saat 10:00'da devrimi başlatıyoruz.",
    "THE": "",
    "IS_ON": "Açık!",
    "YOUR_NAME": "Adınız",
    "YOUR_BEST_EMAIL": "E-posta adresiniz",
    "GET_STARTED_NOW": "Şimdi başlayın!",
    "THERE_IS_NO_PRICE_TOO_GREAT_TO_PAY_FOR_THE_PRIVILEGE_OF_OWNING_YOURSELF": "“Kendine sahip olma ayrıcalığını ödeyemeyecek kadar büyük bir bedel yoktur. - Holton Buggs",

    "DO_YOU_HAVE_AN_IQ_TRAVEL_PACKAGE": "IQ Seyahat paketiniz var mı?",
    "YES": "Evet",
    "NO": "Hayır",

    "GET_IN_STANDBY_CLASS_NOW": "Şimdi Hazırlık dersine katılın!",
    "STANDBY": "Hazırlık",
    "ADD_TO_CART": "Sepete ekleyin",

    "ENTER_YOUR_IQ_USER_ID_OR_USER_NAME": "IQ kullanıcı kimliğinizi veya kullanıcı adınızı girin",
    "CASE_SENSITIVE_SEARCH": "Küçük harfe duyarlı arama",
    "ENTER": "Giriş yapın",
    "CONGRATULATIONS_WE_FOUND_YOUR_ID_AND_YOU_HAVE_A": "Tebrikler! kimliğinizi bulduk ve",
    "CREDIT_TO_USE_TOWARDS_OUR_OPTIONAL_PROMOTIONAL_ENROLLMENT_PACKS": "kredi<br>İsteğe bağlı promosyon kayıt paketlerimizi kullanmak için!",
    "CONTINUE": "DEVAM ET",
    "WERE_SORRY_BUT_WE_CANT_FIND_THAT_IQ_USER_ID_IN_OUR_SYSTEM_TRY_AGAIN": "Maalesef sistemimizde bu IQ Kullanıcı Kimliğini bulamıyoruz. Tekrar deneyin.",

    "OPTIONAL_PROMOTIONAL_ENROLLMENT_PACKS": "İsteğe Bağlı Promosyon Kayıt Paketleri",
    "CHOOSE_YOUR_ENROLLMENT_PACK_TO_BE_BILLED_ON_OR_AFTER_MARCH_11TH": "11 Mart'ta veya sonrasında faturalandırılacak olan kayıt paketinizi seçin",
    "COACH": "Coach",
    "BUSINESS": "Business",
    "FIRST": "First",
    "COACH_CLASS": "Antrenör sınıfı",
    "HOTELS_FLIGHTS_RENTAL_CARS": "Oteller + Uçuşlar + Kiralık Araçlar",
    "BOOMERANGS": "Bumerang",
    "TRAVEL_SAVINGS_BONUSES_ON_HOTELS": "Otellerde Seyahat Tasarrufu Bonusu ve amp; Kiralık arabalar",
    "DUAL_TEAM": "İkili Takım :",
    "LUXURY_EXPERIENCES_GENERAL_RELEASE": "Lüks Deneyimler Genel Yayın",
    "200_BV_BASIC": "200 BV",
    "SELECT_PACK": "Paket seçin",
    "BUSINESS_CLASS": "Business sınıfı",
    "COACH_CLASS_CRUISES": "Antrenör Sınıfı + Turlar",
    "BOOMERANGS_COMMISSIONS_ON_HOTELS": "Bumeranglar, Otellerdeki Komisyonlar &amp; Kiralık arabalar",
    "TRAVEL_SAVINGS_BONUSES_ON_HOTELS": "Otellerde Seyahat Tasarrufu Bonusu &amp; Kiralık arabalar",
    "VIP_LEVEL_2_RESERATIONS": "VIP Seviye 2 Reserasyonları",
    "1_WEEK_PRESALE": "1 Hafta Ön Satış",
    "400_BV_INTERMEDIATE": "400 BV",
    "FIRST_CLASS": "BİRİNCİ Sınıf",
    "BUSINESS_CLASS__HOMES__WEEKS": "Business Class + Evleri + Haftaları + Pazar + Yaşam Tarzı + Devremülk",
    "BOOMERANGS_FULL_COMMISSIONS": "Bumeranglar, Tam Komisyonlar",
    "TRAVEL_SAVINGS_BONUSES_ON_ALL_ELIGIBLE_TRAVEL": "Uygun Seyahatlerde Seyahat Tasarrufu Bonusu &amp; faaliyetler",
    "LIMITED_FOUNDERS_CLUB_PROMOTION": "&nbsp;Sınırlı Kurucu Kulübü Promosyonu",
    "VIP_LEVEL_1_RESERVATIONS": "VIP Seviye 1 Rezervasyonları",
    "2_WEEKS_PRESALE": "2 Hafta Ön Satış",
    "800_BV_FULL": "800 BV",
    "SKIP": "ATLA",

    "SPONSOR_INFORMATION": "Sponsor Bilgisi",
    "SPONSOR_ID_USERNAME": "SPONSOR ID (kullanıcı adı)",
    "SPONSOR_ID_REFERRAL_CODE": "Sponsor Kimliği (Referans Kodu)",
    "SPONSOR_NAME": "Sponsor Adı",
    "PERSONAL_INFORMATION": "Kişisel Bilgiler",
    "FIRST_NAME": "Adı",
    "LAST_NAME": "Soyadı",
    "PRIMARY_PHONE": "Birincil Telefon",
    "MOBILE_PHONE": "Cep Telefonu",
    "EMAIL_ADDRESS": "E-posta Adresi",
    "CONFIRM_EMAIL": "E-posta Adresini konfirme edin",
    "USERNAME":"Kullanıcı adı",
    "REFERRAL_LINK": "Yönlendirme Linki",
    "CONTINUE": "Devam edin",

    "REVIEW_YOUR_ORDER": "Siparişinizi gözden geçirin",
    "ORDER_DETAILS": "Sipariş Detayları",
    "BILLED_ON_MARCH_11TH": "11 Mart tarihinde <br>faturalandırıldı",
    "BILLED_TODAY": "Bugün <br>faturalandırıldı",
    "DIGITAL_TRAINING_KIT": "Dijital Başlangıç Kiti",
    "BILLED_ON_OR_AFTER_MARCH_11TH":"11 Mart'ta veya sonrasında faturalandırıldı",
    "APPLIED_AT_TIME_OF_BILLING":"fatura anında uygulanır",
    "LESS_IQ_CREDIT": "daha az iq kredisi",
    "TOTAL_DUE": "toplam borç",
    "YOU_ACKNOWLEDGE_AND_AGREE_TO_THE_TERMS": "Bugün 49.95 $ olan Dijital Başlangıç Kiti ücretini sizden tahsil eden Özgürlük için Geri Sayım'ın koşullarını onaylıyor ve kabul ediyorsunuz. 11 Mart 2019 veya sonrasında, seçilen kayıt paketinin kalan bakiyesini tahsil ediyor olacağız.",
    "AGREE_TO_TERMS_CONDITIONS": "Şartlar ve Koşulları Kabul Et",
    "AGREE_TO_POLICIES_PROCEDURES": "Politika ve Prosedürleri Kabul Etme",
    "AGREE_TO_SOCIAL_MEDIA_POLICY": "Sosyal Medya Politikasını Kabul Etme",
    "AGREE_TO_PRIVACY_POLICY":"Gizlilik Politikasını Kabul Et",
    "AGREE_TO_ANTI_SPAM_POLICY":"Anti Spam Politikasını Kabul Etme",
    "BILLING_INFORMATION": "Fatura Bilgisi",
    "NAME_ON_CARD": "Kart üzerindeki isim",
    "CARD_NUMBER": "Kart numarası",
    "CVV": "CVV",
    "EXPIRATION_DATE": "Son kullanma tarihi",
    "ADDRESS":"adres",
    "APT_SUITE":"daire / süit",
    "COUNTRY":"ülke",
    "CITY_TOWN": "şehir / kasaba",
    "STATE_PROVINCE": "Eyalet / İl",
    "POSTAL_CODE": "Posta Kodu",
    "CHECKOUT": "Ödeme yapın",

    "THANK_YOU": "Teşekkür ederiz!",
    "THATS_IT_YOURE_OFFICIALLY_A_PART": "Bu kadar! Resmen resmen bir parçası<br>devrim, ve bir<br> başka hiçbir şeye benzemez.<br><br> Yönlendirme kodun burada:",
    "YOUR_USER_ID":"Kullanıcı Kimliğiniz:",
    "ENROLL_YOUR_FIRST_DISTRIBUTOR_NOW":"İlk Distribütörünüzü şimdi kaydettirin!",
    "GO": "BAŞLA!",

    "WE_HAVE_APPLIED_YOUR_CREDIT": "We have applied your credits"
}